alabamaEncode/__init__.py
alabamaEncode/ai_vmaf/__init__.py
alabamaEncode/ai_vmaf/aom_firstpass.py
alabamaEncode/ai_vmaf/perdict.py
alabamaEncode/ai_vmaf/train/__init__.py
alabamaEncode/ai_vmaf/train/train.py
alabamaEncode/binaries/__init__.py
alabamaEncode/binaries/bin_helpers.py
alabamaEncode/cli/__init__.py
alabamaEncode/cli/__main__.py
alabamaEncode/cli/cli_setup/__init__.py
alabamaEncode/cli/cli_setup/autopaths.py
alabamaEncode/cli/cli_setup/cli_args.py
alabamaEncode/cli/cli_setup/paths.py
alabamaEncode/cli/cli_setup/ratecontrol.py
alabamaEncode/cli/cli_setup/res_preset.py
alabamaEncode/cli/cli_setup/validate_files.py
alabamaEncode/cli/cli_setup/video_filters.py
alabamaEncode/conent_analysis/__init__.py
alabamaEncode/conent_analysis/opinionated_vmaf.py
alabamaEncode/conent_analysis/pipelines.py
alabamaEncode/conent_analysis/refine_step.py
alabamaEncode/conent_analysis/chunk/__init__.py
alabamaEncode/conent_analysis/chunk/chunk_analyse_step.py
alabamaEncode/conent_analysis/chunk/final_encode_step.py
alabamaEncode/conent_analysis/chunk/analyze_steps/__init__.py
alabamaEncode/conent_analysis/chunk/analyze_steps/manual_crf.py
alabamaEncode/conent_analysis/chunk/analyze_steps/multires_encode_candidates.py
alabamaEncode/conent_analysis/chunk/analyze_steps/new_grain.py
alabamaEncode/conent_analysis/chunk/analyze_steps/optimised_vbr.py
alabamaEncode/conent_analysis/chunk/analyze_steps/per_scene_grain.py
alabamaEncode/conent_analysis/chunk/analyze_steps/plain_crf.py
alabamaEncode/conent_analysis/chunk/analyze_steps/plain_vbr.py
alabamaEncode/conent_analysis/chunk/analyze_steps/target_vmaf.py
alabamaEncode/conent_analysis/chunk/final_encode_steps/__init__.py
alabamaEncode/conent_analysis/chunk/final_encode_steps/dynamic_target_vmaf.py
alabamaEncode/conent_analysis/chunk/final_encode_steps/dynamic_target_vmaf_vbr.py
alabamaEncode/conent_analysis/chunk/final_encode_steps/multires_encode_finals.py
alabamaEncode/conent_analysis/chunk/final_encode_steps/plain.py
alabamaEncoder-0.5.4.dist-info/LICENSE
alabamaEncoder-0.5.4.dist-info/METADATA
alabamaEncoder-0.5.4.dist-info/WHEEL
alabamaEncoder-0.5.4.dist-info/entry_points.txt
alabamaEncoder-0.5.4.dist-info/top_level.txt
alabamaEncoder-0.5.4.dist-info/RECORD
