Metadata-Version: 2.2
Name: alabamaEncoder
Version: 0.5.4
Requires-Python: >=3.12.3
License-File: LICENSE
Requires-Dist: scenedetect
Requires-Dist: tqdm
Requires-Dist: celery
Requires-Dist: redis
Requires-Dist: psutil
Requires-Dist: opencv-contrib-python
Requires-Dist: requests
Requires-Dist: torf
Requires-Dist: websockets
Requires-Dist: scipy
Requires-Dist: numpy
Requires-Dist: scikit-image
Requires-Dist: argparse_range
Requires-Dist: matplotlib
Dynamic: requires-dist
Dynamic: requires-python
